coalgo/__init__.py
coalgo-0.0.0.dist-info/LICENSE
coalgo-0.0.0.dist-info/METADATA
coalgo-0.0.0.dist-info/WHEEL
coalgo-0.0.0.dist-info/top_level.txt
coalgo-0.0.0.dist-info/RECORD
